hregex/__init__.py
hregex/__version__.py
hregex-1.0.1.dist-info/licenses/LICENSE
hregex-1.0.1.dist-info/METADATA
hregex-1.0.1.dist-info/WHEEL
hregex-1.0.1.dist-info/top_level.txt
hregex-1.0.1.dist-info/RECORD
