Metadata-Version: 2.4
Name: hregex
Version: 1.0.1
Summary: HRegex: A streamlined approach to simplifying regex creation.
Author: Farhan Ali
Author-email: i.farhanali.dev@gmail.com
Keywords: regex,human regex,easy regex,python regex,farhan ali
Classifier: Programming Language :: Python :: 3
Classifier: License :: OSI Approved :: Apache Software License
Classifier: Operating System :: OS Independent
License-File: LICENSE
Dynamic: author
Dynamic: author-email
Dynamic: classifier
Dynamic: description
Dynamic: description-content-type
Dynamic: keywords
Dynamic: license-file
Dynamic: summary
